MANIFEST.in
README.md
README.pypi.rst
dev-requirements.txt
requirements.txt
setup.py
diagrams/sheepdog_exporter.svg
sheepdog_exporter/__init__.py
sheepdog_exporter/sheepdog_exporter.py
sheepdog_exporter.egg-info/PKG-INFO
sheepdog_exporter.egg-info/SOURCES.txt
sheepdog_exporter.egg-info/dependency_links.txt
sheepdog_exporter.egg-info/entry_points.txt
sheepdog_exporter.egg-info/requires.txt
sheepdog_exporter.egg-info/top_level.txt
sheepdog_exporter.egg-info/zip-safe
test/test.py