Metadata-Version: 1.1
Name: sheepdog-exporter
Version: 0.3.0
Summary: Export metadata from the DCP Sheepdog API.
Home-page: https://github.com/david4096/sheepdog-exporter
Author: David Steinberg
Author-email: davidcs@ucsc.edu
License: Apache License 2.0
Keywords: genomics,metadata,NIHDataCommons
Platform: UNKNOWN
Classifier: Development Status :: 3 - Alpha
Classifier: Intended Audience :: Science/Research
Classifier: License :: OSI Approved :: Apache Software License
Classifier: Natural Language :: English
Classifier: Programming Language :: Python :: 2.7
Classifier: Topic :: Scientific/Engineering :: Bio-Informatics
